<?xml version="1.0"?>
<project
	xsi:schemaLocation="http://maven.apache.org/DECORATION/1.0.0 http://maven.apache.org/xsd/decoration-1.0.0.xsd"
	xmlns="http://maven.apache.org/DECORATION/1.0.0"
	xmlns:xsi="http://www.w3.org/2001/XMLSchema-instance">

	<skin>
		<groupId>org.apache.maven.skins</groupId>
		<artifactId>maven-fluido-skin</artifactId>
		<version>2.0.0-M8</version>
	</skin>

	<body>
		<menu>
			<item name="Data Structures" href="data_structures.html" />
			<item name="OpenAPI" href="openapi/README.html" />
			<item name="Diagrams" href="puml/" />
		</menu>
		<menu ref="reports" />
	</body>
</project>